plone.caching-2.0.2-py3.13-nspkg.pth
plone/caching/__init__.py
plone/caching/configure.zcml
plone/caching/hooks.py
plone/caching/interfaces.py
plone/caching/lookup.py
plone/caching/operations.py
plone/caching/testing.py
plone/caching/utils.py
plone/caching/tests/__init__.py
plone/caching/tests/test_hooks.py
plone/caching/tests/test_lookup.py
plone/caching/tests/test_operations.py
plone/caching/tests/test_utils.py
plone_caching-2.0.2.dist-info/METADATA
plone_caching-2.0.2.dist-info/WHEEL
plone_caching-2.0.2.dist-info/namespace_packages.txt
plone_caching-2.0.2.dist-info/top_level.txt
plone_caching-2.0.2.dist-info/RECORD
